{"data":{"id":46613,"title":"Jean Garling collection : portrait photoprints, 1920-1950","primoId":"ADLIB110311639","slug":"adlib110311639","shortcode":"","imageUrl":"https:\/\/dxlab.sl.nsw.gov.au\/images-newselfwales\/selfie1525856485643.jpg","content":"army officers, dancers, fencing (sports), physiotherapists, portraits","imageType":"portrait","date":"2018-05-09 09:01:25","dateText":"1920-1950","timestamp":"","instagramUsername":"","featuredMedia":{"sourceUrl":"https:\/\/dxlab.sl.nsw.gov.au\/images-newselfwales\/selfie1525856485643.jpg","sizes":{"medium":{"sourceUrl":"https:\/\/dxlab.sl.nsw.gov.au\/images-newselfwales\/selfie1525856485643-253x300.jpg","width":253,"height":300,"__typename":"MediaSize"},"full":{"sourceUrl":"https:\/\/dxlab.sl.nsw.gov.au\/images-newselfwales\/selfie1525856485643.jpg","width":886,"height":1050,"__typename":"MediaSize"},"__typename":"MediaSizes"},"__typename":"Media"},"__typename":"NewSelfWalesPortrait"}}