{"data":[{"id":36220,"title":"T. [Thomas Brailey ?] Brailey","primoId":"ADLIB110042509","slug":"adlib110042509","shortcode":"","imageUrl":"https:\/\/dxlab.sl.nsw.gov.au\/images-newselfwales\/selfie1525672314688.jpg","content":"interiors, portraits, Adult Males","imageType":"portrait","date":"2018-05-07 05:51:54","dateText":"1870-1875","timestamp":"","instagramUsername":"","featuredMedia":{"sourceUrl":"https:\/\/dxlab.sl.nsw.gov.au\/images-newselfwales\/selfie1525672314688.jpg","sizes":{"medium":{"sourceUrl":"https:\/\/dxlab.sl.nsw.gov.au\/images-newselfwales\/selfie1525672314688-223x300.jpg","width":223,"height":300,"__typename":"MediaSize"},"full":{"sourceUrl":"https:\/\/dxlab.sl.nsw.gov.au\/images-newselfwales\/selfie1525672314688.jpg","width":779,"height":1050,"__typename":"MediaSize"},"__typename":"MediaSizes"},"__typename":"Media"},"__typename":"NewSelfWalesPortrait"},{"id":66857,"title":"Album of photographs \/ photographed by Max Dupain","primoId":"ADLIB110332870","slug":"adlib110332870-fl431832","shortcode":"","imageUrl":"https:\/\/dxlab.sl.nsw.gov.au\/images-newselfwales\/selfie-1535681284873-.jpg","content":"portraits, landscapes (views), Yerranderie (Upper Burragorang, N.S.W.), Burragorang (N.S.W.)","imageType":"portrait","date":"2018-09-03 15:25:43","dateText":"1940","timestamp":"","instagramUsername":"","featuredMedia":{"sourceUrl":"https:\/\/dxlab.sl.nsw.gov.au\/images-newselfwales\/selfie-1535681284873-.jpg","sizes":{"medium":{"sourceUrl":"https:\/\/dxlab.sl.nsw.gov.au\/images-newselfwales\/selfie-1535681284873--e1535952327963-300x289.jpg","width":300,"height":289,"__typename":"MediaSize"},"full":{"sourceUrl":"https:\/\/dxlab.sl.nsw.gov.au\/images-newselfwales\/selfie-1535681284873-.jpg","width":506,"height":488,"__typename":"MediaSize"},"__typename":"MediaSizes"},"__typename":"Media"},"__typename":"NewSelfWalesPortrait"},{"id":6954,"title":"John Rae - portraits of Australian Aborigines, 1842","primoId":"ADLIB110328058","slug":"adlib110328058","shortcode":"","imageUrl":"https:\/\/dxlab.sl.nsw.gov.au\/images-newselfwales\/selfie1523884150750.jpg","content":"Aboriginal peoples (Australians), colonial art, portraits, Adult Females, Adult Males","imageType":"portrait","date":"2018-04-16 13:09:10","dateText":"1842","timestamp":"","instagramUsername":"","featuredMedia":{"sourceUrl":"https:\/\/dxlab.sl.nsw.gov.au\/images-newselfwales\/selfie1523884150750.jpg","sizes":{"medium":{"sourceUrl":"https:\/\/dxlab.sl.nsw.gov.au\/images-newselfwales\/selfie1523884150750-221x300.jpg","width":221,"height":300,"__typename":"MediaSize"},"full":{"sourceUrl":"https:\/\/dxlab.sl.nsw.gov.au\/images-newselfwales\/selfie1523884150750.jpg","width":773,"height":1050,"__typename":"MediaSize"},"__typename":"MediaSizes"},"__typename":"Media"},"__typename":"NewSelfWalesPortrait"},{"id":51835,"title":"Commander Robert Johnston R.N., 1856 \/ Richard Noble","primoId":"ADLIB110338747","slug":"adlib110338747","shortcode":"","imageUrl":"https:\/\/dxlab.sl.nsw.gov.au\/images-newselfwales\/selfie1525936639353.jpg","content":"portraits, Art, Colonial--New South Wales., Adult Males","imageType":"portrait","date":"2018-05-10 07:17:19","dateText":"1856","timestamp":"","instagramUsername":"","featuredMedia":{"sourceUrl":"https:\/\/dxlab.sl.nsw.gov.au\/images-newselfwales\/selfie1525936639353.jpg","sizes":{"medium":{"sourceUrl":"https:\/\/dxlab.sl.nsw.gov.au\/images-newselfwales\/selfie1525936639353-e1534718862664-242x300.jpg","width":242,"height":300,"__typename":"MediaSize"},"full":{"sourceUrl":"https:\/\/dxlab.sl.nsw.gov.au\/images-newselfwales\/selfie1525936639353.jpg","width":811,"height":1005,"__typename":"MediaSize"},"__typename":"MediaSizes"},"__typename":"Media"},"__typename":"NewSelfWalesPortrait"},{"id":47639,"title":"[Elizabeth Macquarie, ca. 1819 - watercolour on ivory miniature]","primoId":"ADLIB110322733","slug":"adlib110322733","shortcode":"","imageUrl":"https:\/\/dxlab.sl.nsw.gov.au\/images-newselfwales\/selfie1525918638122.jpg","content":"miniatures, picture frames, portraits, Adult Females","imageType":"portrait","date":"2018-05-10 02:17:18","dateText":"ca. 1819","timestamp":"","instagramUsername":"","featuredMedia":{"sourceUrl":"https:\/\/dxlab.sl.nsw.gov.au\/images-newselfwales\/selfie1525918638122.jpg","sizes":{"medium":{"sourceUrl":"https:\/\/dxlab.sl.nsw.gov.au\/images-newselfwales\/selfie1525918638122-e1534736840205-265x300.jpg","width":265,"height":300,"__typename":"MediaSize"},"full":{"sourceUrl":"https:\/\/dxlab.sl.nsw.gov.au\/images-newselfwales\/selfie1525918638122.jpg","width":798,"height":903,"__typename":"MediaSize"},"__typename":"MediaSizes"},"__typename":"Media"},"__typename":"NewSelfWalesPortrait"},{"id":22713,"title":"Unidentified passenger from Union Co ship which brought racehorse","primoId":"ADLIB110034390","slug":"adlib110034390","shortcode":"","imageUrl":"https:\/\/dxlab.sl.nsw.gov.au\/images-newselfwales\/selfie1525067961724.jpg","content":"portraits, Adult Males","imageType":"portrait","date":"2018-04-30 05:59:20","dateText":"1930s ?","timestamp":"","instagramUsername":"","featuredMedia":{"sourceUrl":"https:\/\/dxlab.sl.nsw.gov.au\/images-newselfwales\/selfie1525067961724.jpg","sizes":{"medium":{"sourceUrl":"https:\/\/dxlab.sl.nsw.gov.au\/images-newselfwales\/selfie1525067961724-300x220.jpg","width":300,"height":220,"__typename":"MediaSize"},"full":{"sourceUrl":"https:\/\/dxlab.sl.nsw.gov.au\/images-newselfwales\/selfie1525067961724.jpg","width":1400,"height":1028,"__typename":"MediaSize"},"__typename":"MediaSizes"},"__typename":"Media"},"__typename":"NewSelfWalesPortrait"},{"id":16524,"title":"Miss [Elizabeth Doughty ?] Creasy [Creasey ?]","primoId":"ADLIB110042751","slug":"adlib110042751","shortcode":"","imageUrl":"https:\/\/dxlab.sl.nsw.gov.au\/images-newselfwales\/selfie1524039989044.jpg","content":"interiors, portraits, girls","imageType":"portrait","date":"2018-04-18 08:26:29","dateText":"1870-1875","timestamp":"","instagramUsername":"","featuredMedia":{"sourceUrl":"https:\/\/dxlab.sl.nsw.gov.au\/images-newselfwales\/selfie1524039989044.jpg","sizes":{"medium":{"sourceUrl":"https:\/\/dxlab.sl.nsw.gov.au\/images-newselfwales\/selfie1524039989044-e1537420175520-224x300.jpg","width":224,"height":300,"__typename":"MediaSize"},"full":{"sourceUrl":"https:\/\/dxlab.sl.nsw.gov.au\/images-newselfwales\/selfie1524039989044.jpg","width":750,"height":1005,"__typename":"MediaSize"},"__typename":"MediaSizes"},"__typename":"Media"},"__typename":"NewSelfWalesPortrait"},{"id":45699,"title":"Captain Robert Monro, captain of the ship Avondhu, ca. 1866 \/ photographer unknown","primoId":"ADLIB110346043","slug":"adlib110346043","shortcode":"","imageUrl":"https:\/\/dxlab.sl.nsw.gov.au\/images-newselfwales\/selfie1525853097850.jpg","content":"portraits, ships' captains, Adult Males","imageType":"portrait","date":"2018-05-09 08:04:58","dateText":"ca. 1866","timestamp":"","instagramUsername":"","featuredMedia":{"sourceUrl":"https:\/\/dxlab.sl.nsw.gov.au\/images-newselfwales\/selfie1525853097850.jpg","sizes":{"medium":{"sourceUrl":"https:\/\/dxlab.sl.nsw.gov.au\/images-newselfwales\/selfie1525853097850-e1536633132254-181x300.jpg","width":181,"height":300,"__typename":"MediaSize"},"full":{"sourceUrl":"https:\/\/dxlab.sl.nsw.gov.au\/images-newselfwales\/selfie1525853097850.jpg","width":595,"height":987,"__typename":"MediaSize"},"__typename":"MediaSizes"},"__typename":"Media"},"__typename":"NewSelfWalesPortrait"},{"id":49835,"title":"Mr F. H. Needs, dancing teacher, ca. 1875 \/ photographer J. H. Newman","primoId":"ADLIB110346365","slug":"adlib110346365","shortcode":"","imageUrl":"https:\/\/dxlab.sl.nsw.gov.au\/images-newselfwales\/selfie1525927310514.jpg","content":"portraits, dance studios, teachers, Adult Males","imageType":"portrait","date":"2018-05-10 04:41:50","dateText":"ca. 1875","timestamp":"","instagramUsername":"","featuredMedia":{"sourceUrl":"https:\/\/dxlab.sl.nsw.gov.au\/images-newselfwales\/selfie1525927310514.jpg","sizes":{"medium":{"sourceUrl":"https:\/\/dxlab.sl.nsw.gov.au\/images-newselfwales\/selfie1525927310514-180x300.jpg","width":180,"height":300,"__typename":"MediaSize"},"full":{"sourceUrl":"https:\/\/dxlab.sl.nsw.gov.au\/images-newselfwales\/selfie1525927310514.jpg","width":630,"height":1050,"__typename":"MediaSize"},"__typename":"MediaSizes"},"__typename":"Media"},"__typename":"NewSelfWalesPortrait"},{"id":67216,"title":"Sydney Town street portraits, March 2014-August 2015 \/ photographs by Jon Lewis","primoId":"ADLIB110581269","slug":"adlib110581269-fl3811162","shortcode":"","imageUrl":"https:\/\/dxlab.sl.nsw.gov.au\/images-newselfwales\/selfie-1535681565990-.jpg","content":"portraits, Sydney (N.S.W.), Portrait photography--New South Wales--21st century., Street photography--New South Wales--Sydney, Aboriginal Australians--New South Wales--Portraits","imageType":"portrait","date":"2018-09-03 14:16:03","dateText":"March 2014-August 2015","timestamp":"","instagramUsername":"","featuredMedia":{"sourceUrl":"https:\/\/dxlab.sl.nsw.gov.au\/images-newselfwales\/selfie-1535681565990-.jpg","sizes":{"medium":{"sourceUrl":"https:\/\/dxlab.sl.nsw.gov.au\/images-newselfwales\/selfie-1535681565990--300x200.jpg","width":300,"height":200,"__typename":"MediaSize"},"full":{"sourceUrl":"https:\/\/dxlab.sl.nsw.gov.au\/images-newselfwales\/selfie-1535681565990-.jpg","width":500,"height":333,"__typename":"MediaSize"},"__typename":"MediaSizes"},"__typename":"Media"},"__typename":"NewSelfWalesPortrait"},{"id":22439,"title":"Tom Crommelin, ca. 1880 \/ photographer unknown","primoId":"ADLIB110341793","slug":"adlib110341793","shortcode":"","imageUrl":"https:\/\/dxlab.sl.nsw.gov.au\/images-newselfwales\/selfie1525066638731.jpg","content":"portraits, Adult Males","imageType":"portrait","date":"2018-04-30 05:37:17","dateText":"ca. 1880","timestamp":"","instagramUsername":"","featuredMedia":{"sourceUrl":"https:\/\/dxlab.sl.nsw.gov.au\/images-newselfwales\/selfie1525066638731.jpg","sizes":{"medium":{"sourceUrl":"https:\/\/dxlab.sl.nsw.gov.au\/images-newselfwales\/selfie1525066638731-230x300.jpg","width":230,"height":300,"__typename":"MediaSize"},"full":{"sourceUrl":"https:\/\/dxlab.sl.nsw.gov.au\/images-newselfwales\/selfie1525066638731.jpg","width":804,"height":1050,"__typename":"MediaSize"},"__typename":"MediaSizes"},"__typename":"Media"},"__typename":"NewSelfWalesPortrait"},{"id":11281,"title":"Thomas Jones \/ [crayotype studio portrait] E. Dalton del., Sydney, Dec., 1859","primoId":"ADLIB110324673","slug":"adlib110324673","shortcode":"","imageUrl":"https:\/\/dxlab.sl.nsw.gov.au\/images-newselfwales\/selfie1524019537287.jpg","content":"graziers, portraits, Adult Males","imageType":"portrait","date":"2018-04-18 02:45:37","dateText":"1859","timestamp":"","instagramUsername":"","featuredMedia":{"sourceUrl":"https:\/\/dxlab.sl.nsw.gov.au\/images-newselfwales\/selfie1524019537287.jpg","sizes":{"medium":{"sourceUrl":"https:\/\/dxlab.sl.nsw.gov.au\/images-newselfwales\/selfie1524019537287-245x300.jpg","width":245,"height":300,"__typename":"MediaSize"},"full":{"sourceUrl":"https:\/\/dxlab.sl.nsw.gov.au\/images-newselfwales\/selfie1524019537287.jpg","width":856,"height":1050,"__typename":"MediaSize"},"__typename":"MediaSizes"},"__typename":"Media"},"__typename":"NewSelfWalesPortrait"},{"id":68985,"title":"\ud83e\udd84Jin Yahan","primoId":"","slug":"","shortcode":"Bmo6ZbqBERH","imageUrl":"https:\/\/dxlab.sl.nsw.gov.au\/images-newselfwales\/selfie-1536213683820-.jpg","content":"\ud83d\ude06","imageType":"instagram_selfie","date":"2018-09-07 09:11:21","dateText":"","timestamp":1534636148,"instagramUsername":"jane_jyh","featuredMedia":{"sourceUrl":"https:\/\/dxlab.sl.nsw.gov.au\/images-newselfwales\/selfie-1536213683820-.jpg","sizes":{"medium":{"sourceUrl":"https:\/\/dxlab.sl.nsw.gov.au\/images-newselfwales\/selfie-1536213683820--300x300.jpg","width":300,"height":300,"__typename":"MediaSize"},"full":{"sourceUrl":"https:\/\/dxlab.sl.nsw.gov.au\/images-newselfwales\/selfie-1536213683820-.jpg","width":1080,"height":1080,"__typename":"MediaSize"},"__typename":"MediaSizes"},"__typename":"Media"},"__typename":"NewSelfWalesInstagramSelfie"},{"id":67678,"title":"Tim Burgess","primoId":"","slug":"","shortcode":"Bly4jwChIyU","imageUrl":"https:\/\/dxlab.sl.nsw.gov.au\/images-newselfwales\/selfie-1535700852635-.jpg","content":"I\u2019m nerdy enough to admit that this new #doublehelix staircase has made my morning. #NewSelfWales","imageType":"instagram_selfie","date":"2018-09-03 08:41:12","dateText":"","timestamp":1532823378,"instagramUsername":"t__burgess","featuredMedia":{"sourceUrl":"https:\/\/dxlab.sl.nsw.gov.au\/images-newselfwales\/selfie-1535700852635-.jpg","sizes":{"medium":{"sourceUrl":"https:\/\/dxlab.sl.nsw.gov.au\/images-newselfwales\/selfie-1535700852635--300x300.jpg","width":300,"height":300,"__typename":"MediaSize"},"full":{"sourceUrl":"https:\/\/dxlab.sl.nsw.gov.au\/images-newselfwales\/selfie-1535700852635-.jpg","width":1080,"height":1080,"__typename":"MediaSize"},"__typename":"MediaSizes"},"__typename":"Media"},"__typename":"NewSelfWalesInstagramSelfie"},{"id":72463,"title":"AnythingWorxwithGrace\u2122\ufe0f","primoId":"","slug":"","shortcode":"Bgcj2EKFgnp","imageUrl":"https:\/\/dxlab.sl.nsw.gov.au\/images-newselfwales\/selfie-1537527758406-.jpg","content":"Emgraced.\nEmbracing my limitations,\nMy imperfections, my flaws\nIncluding acne\/pimples \ud83e\udd23\ud83d\ude02\ud83d\ude1c \u2022\u2022\u2022\u2022\u2022\u2022\u2022\u2022\u2022\u2022\u2022\u2022\u2022\u2022\u2022\u2022\u2022\u2022\u2022\u2022\u2022\u2022\u2022\u2022\u2022 \u2022\u2022\u2022\u2022\u2022\u2022\u2022\u2022\u2022\u2022\u2022\u2022\u2022\u2022\u2022\u2022\u2022\u2022\u2022\u2022\u2022\u2022\u2022\u2022\u2022 Seriously annoyed that at my late 30s, I\u2019m still having acne\/ pimples like 16, arrrg! \nAlthough its part of hormonal imbalance, I\u2019m still trying to see the positive side of it, by listening to my body frequently, admitting that I\u2019m guilty of staying up late, lack of sleep, binge watching Netflix and having all the excuses to exercise. \nOn a lighter note,  these 3major breakouts made me feel I\u2019m still on my teens, hence the #90shairstyle \ud83e\udd23\nOh well, #scrunchies are back!!! \u2022\u2022\u2022\u2022\u2022\u2022\u2022\u2022\u2022\u2022\u2022\u2022\u2022\u2022\u2022\u2022\u2022\u2022\u2022\u2022\u2022\u2022\u2022\u2022\u2022\u2022\u2022\u2022\n\u2022\u2022\u2022\u2022\u2022\u2022\u2022\u2022\u2022\u2022\u2022\u2022\u2022\u2022\u2022\u2022\u2022\u2022\u2022\u2022\u2022\u2022\u2022\u2022\u2022\u2022\u2022\u2022 #cysticacne #cysterhood #cysters #PCOSuLUVME #pcos #pcosawareness #pcosweightloss #emGraced #gracified #graceaunlimited #GRACEward #selflove #selfcare #firstloveyourself #weekendvibes #thebodyloverevolution #morenaglow #diabetterG #diabetes #diabetesawareness #newselfwales","imageType":"instagram_selfie","date":"2018-09-24 12:08:12","dateText":"","timestamp":1521336769,"instagramUsername":"anythingworxwithgrace","featuredMedia":{"sourceUrl":"https:\/\/dxlab.sl.nsw.gov.au\/images-newselfwales\/selfie-1537527758406-.jpg","sizes":{"medium":{"sourceUrl":"https:\/\/dxlab.sl.nsw.gov.au\/images-newselfwales\/selfie-1537527758406--300x300.jpg","width":300,"height":300,"__typename":"MediaSize"},"full":{"sourceUrl":"https:\/\/dxlab.sl.nsw.gov.au\/images-newselfwales\/selfie-1537527758406-.jpg","width":1080,"height":1076,"__typename":"MediaSize"},"__typename":"MediaSizes"},"__typename":"Media"},"__typename":"NewSelfWalesInstagramSelfie"},{"id":61705,"title":"Tatiana Samokhina","primoId":"","slug":"","shortcode":"BmVWvMkhZCW","imageUrl":"https:\/\/dxlab.sl.nsw.gov.au\/images-newselfwales\/selfie-1533980404484-.jpg","content":"Let's see what happens.\n#newselfwales","imageType":"instagram_selfie","date":"2018-09-03 09:22:06","dateText":"","timestamp":1533979917,"instagramUsername":"tatianasamokhina","featuredMedia":{"sourceUrl":"https:\/\/dxlab.sl.nsw.gov.au\/images-newselfwales\/selfie-1533980404484-.jpg","sizes":{"medium":{"sourceUrl":"https:\/\/dxlab.sl.nsw.gov.au\/images-newselfwales\/selfie-1533980404484--240x300.jpg","width":240,"height":300,"__typename":"MediaSize"},"full":{"sourceUrl":"https:\/\/dxlab.sl.nsw.gov.au\/images-newselfwales\/selfie-1533980404484-.jpg","width":712,"height":890,"__typename":"MediaSize"},"__typename":"MediaSizes"},"__typename":"Media"},"__typename":"NewSelfWalesInstagramSelfie"},{"id":104678,"title":"Flynn, Steph, Romy, Jeffrey n Gordo","primoId":"","slug":"","shortcode":"","imageUrl":"https:\/\/dxlab.sl.nsw.gov.au\/images-newselfwales\/selfie-1547798345332.png","content":"Flynn, Steph, Romy, Jeffrey n Gordo","imageType":"gallery_selfie","date":"2019-01-18 18:59:05","dateText":"","timestamp":"","instagramUsername":"","featuredMedia":{"sourceUrl":"https:\/\/dxlab.sl.nsw.gov.au\/images-newselfwales\/selfie-1547798345332.png","sizes":{"medium":{"sourceUrl":"https:\/\/dxlab.sl.nsw.gov.au\/images-newselfwales\/selfie-1547798345332-300x300.png","width":300,"height":300,"__typename":"MediaSize"},"full":{"sourceUrl":"https:\/\/dxlab.sl.nsw.gov.au\/images-newselfwales\/selfie-1547798345332.png","width":1080,"height":1080,"__typename":"MediaSize"},"__typename":"MediaSizes"},"__typename":"Media"},"__typename":"NewSelfWalesGallerySelfie"},{"id":85223,"title":"Ariq","primoId":"","slug":"","shortcode":"","imageUrl":"https:\/\/dxlab.sl.nsw.gov.au\/images-newselfwales\/selfie-1541550735418.png","content":"Ariq","imageType":"gallery_selfie","date":"2018-11-07 11:32:15","dateText":"","timestamp":"","instagramUsername":"","featuredMedia":{"sourceUrl":"https:\/\/dxlab.sl.nsw.gov.au\/images-newselfwales\/selfie-1541550735418.png","sizes":{"medium":{"sourceUrl":"https:\/\/dxlab.sl.nsw.gov.au\/images-newselfwales\/selfie-1541550735418-300x300.png","width":300,"height":300,"__typename":"MediaSize"},"full":{"sourceUrl":"https:\/\/dxlab.sl.nsw.gov.au\/images-newselfwales\/selfie-1541550735418.png","width":1080,"height":1080,"__typename":"MediaSize"},"__typename":"MediaSizes"},"__typename":"Media"},"__typename":"NewSelfWalesGallerySelfie"},{"id":99425,"title":"megan","primoId":"","slug":"","shortcode":"","imageUrl":"https:\/\/dxlab.sl.nsw.gov.au\/images-newselfwales\/selfie-1546397873244.png","content":"megan","imageType":"gallery_selfie","date":"2019-01-02 13:57:53","dateText":"","timestamp":"","instagramUsername":"","featuredMedia":{"sourceUrl":"https:\/\/dxlab.sl.nsw.gov.au\/images-newselfwales\/selfie-1546397873244.png","sizes":{"medium":{"sourceUrl":"https:\/\/dxlab.sl.nsw.gov.au\/images-newselfwales\/selfie-1546397873244-300x300.png","width":300,"height":300,"__typename":"MediaSize"},"full":{"sourceUrl":"https:\/\/dxlab.sl.nsw.gov.au\/images-newselfwales\/selfie-1546397873244.png","width":1080,"height":1080,"__typename":"MediaSize"},"__typename":"MediaSizes"},"__typename":"Media"},"__typename":"NewSelfWalesGallerySelfie"},{"id":107800,"title":"Allyson","primoId":"","slug":"","shortcode":"","imageUrl":"https:\/\/dxlab.sl.nsw.gov.au\/images-newselfwales\/selfie-1548891514230.png","content":"Allyson","imageType":"gallery_selfie","date":"2019-01-31 10:38:34","dateText":"","timestamp":"","instagramUsername":"","featuredMedia":{"sourceUrl":"https:\/\/dxlab.sl.nsw.gov.au\/images-newselfwales\/selfie-1548891514230.png","sizes":{"medium":{"sourceUrl":"https:\/\/dxlab.sl.nsw.gov.au\/images-newselfwales\/selfie-1548891514230-300x300.png","width":300,"height":300,"__typename":"MediaSize"},"full":{"sourceUrl":"https:\/\/dxlab.sl.nsw.gov.au\/images-newselfwales\/selfie-1548891514230.png","width":1080,"height":1080,"__typename":"MediaSize"},"__typename":"MediaSizes"},"__typename":"Media"},"__typename":"NewSelfWalesGallerySelfie"}]}