{"data":[{"id":49711,"title":"Jenny, \/ Native of Port Sorell, \/ Van Diemen's Land \/ by T. Bock","primoId":"ADLIB110327053","slug":"adlib110327053","shortcode":"","imageUrl":"https:\/\/dxlab.sl.nsw.gov.au\/images-newselfwales\/selfie1525926765773.jpg","content":"portraits, Tasmanian Aboriginal peoples, Adult Females","imageType":"portrait","date":"2018-05-10 04:32:45","dateText":"ca. 1837","timestamp":"","instagramUsername":"","featuredMedia":{"sourceUrl":"https:\/\/dxlab.sl.nsw.gov.au\/images-newselfwales\/selfie1525926765773.jpg","sizes":{"medium":{"sourceUrl":"https:\/\/dxlab.sl.nsw.gov.au\/images-newselfwales\/selfie1525926765773-e1537762735124-218x300.jpg","width":218,"height":300,"__typename":"MediaSize"},"full":{"sourceUrl":"https:\/\/dxlab.sl.nsw.gov.au\/images-newselfwales\/selfie1525926765773.jpg","width":708,"height":973,"__typename":"MediaSize"},"__typename":"MediaSizes"},"__typename":"Media"},"__typename":"NewSelfWalesPortrait"},{"id":56768,"title":"Soviet whaling fleet in Sydney docks at International Terminal","primoId":"ADLIB110073720","slug":"adlib110073720","shortcode":"","imageUrl":"https:\/\/dxlab.sl.nsw.gov.au\/images-newselfwales\/d7_28567.jpg","content":"portraits, Russians, ships' captains, smoking, uniforms, International Passenger Terminal (Circular Quay, Sydney, N.S.W.), Adult Males","imageType":"portrait","date":"2018-05-15 10:10:48","dateText":"May 1968","timestamp":"","instagramUsername":"","featuredMedia":{"sourceUrl":"https:\/\/dxlab.sl.nsw.gov.au\/images-newselfwales\/d7_28567.jpg","sizes":{"medium":{"sourceUrl":"https:\/\/dxlab.sl.nsw.gov.au\/images-newselfwales\/d7_28567-290x300.jpg","width":290,"height":300,"__typename":"MediaSize"},"full":{"sourceUrl":"https:\/\/dxlab.sl.nsw.gov.au\/images-newselfwales\/d7_28567.jpg","width":1853,"height":1920,"__typename":"MediaSize"},"__typename":"MediaSizes"},"__typename":"Media"},"__typename":"NewSelfWalesPortrait"},{"id":8855,"title":"NSW servicemen portraits, 1918-19 - Herbert William Kellard","primoId":"ADLIB110322353","slug":"adlib110322353","shortcode":"","imageUrl":"https:\/\/dxlab.sl.nsw.gov.au\/images-newselfwales\/selfie1523894139504.jpg","content":"soldiers, uniforms, Adult Males","imageType":"portrait","date":"2018-04-16 15:55:39","dateText":"1918-1919","timestamp":"","instagramUsername":"","featuredMedia":{"sourceUrl":"https:\/\/dxlab.sl.nsw.gov.au\/images-newselfwales\/selfie1523894139504.jpg","sizes":{"medium":{"sourceUrl":"https:\/\/dxlab.sl.nsw.gov.au\/images-newselfwales\/selfie1523894139504-e1536724302397-170x300.jpg","width":170,"height":300,"__typename":"MediaSize"},"full":{"sourceUrl":"https:\/\/dxlab.sl.nsw.gov.au\/images-newselfwales\/selfie1523894139504.jpg","width":527,"height":929,"__typename":"MediaSize"},"__typename":"MediaSizes"},"__typename":"Media"},"__typename":"NewSelfWalesPortrait"},{"id":49951,"title":"Arthur Chipperfield, Australia-England Test, summer 1936-1937","primoId":"ADLIB110029529","slug":"adlib110029529","shortcode":"","imageUrl":"https:\/\/dxlab.sl.nsw.gov.au\/images-newselfwales\/selfie1525927934144.jpg","content":"caps, cricketers, portraits, Sydney Cricket Ground (Sydney, N.S.W.), Adult Males","imageType":"portrait","date":"2018-05-10 04:52:14","dateText":"24\/11\/1936","timestamp":"","instagramUsername":"","featuredMedia":{"sourceUrl":"https:\/\/dxlab.sl.nsw.gov.au\/images-newselfwales\/selfie1525927934144.jpg","sizes":{"medium":{"sourceUrl":"https:\/\/dxlab.sl.nsw.gov.au\/images-newselfwales\/selfie1525927934144-e1534230122405-221x300.jpg","width":221,"height":300,"__typename":"MediaSize"},"full":{"sourceUrl":"https:\/\/dxlab.sl.nsw.gov.au\/images-newselfwales\/selfie1525927934144.jpg","width":737,"height":1000,"__typename":"MediaSize"},"__typename":"MediaSizes"},"__typename":"Media"},"__typename":"NewSelfWalesPortrait"},{"id":43427,"title":"John Fairfax, newspaper proprietor, ca. 1861 \/ unknown photographer","primoId":"ADLIB110162872","slug":"adlib110162872","shortcode":"","imageUrl":"https:\/\/dxlab.sl.nsw.gov.au\/images-newselfwales\/selfie1525836377048.jpg","content":"politicians, portraits, publishers, Adult Males","imageType":"portrait","date":"2018-05-09 03:26:17","dateText":"ca. 1861","timestamp":"","instagramUsername":"","featuredMedia":{"sourceUrl":"https:\/\/dxlab.sl.nsw.gov.au\/images-newselfwales\/selfie1525836377048.jpg","sizes":{"medium":{"sourceUrl":"https:\/\/dxlab.sl.nsw.gov.au\/images-newselfwales\/selfie1525836377048-e1537504515396-234x300.jpg","width":234,"height":300,"__typename":"MediaSize"},"full":{"sourceUrl":"https:\/\/dxlab.sl.nsw.gov.au\/images-newselfwales\/selfie1525836377048.jpg","width":784,"height":1005,"__typename":"MediaSize"},"__typename":"MediaSizes"},"__typename":"Media"},"__typename":"NewSelfWalesPortrait"},{"id":53962,"title":"Miss Australia 1965 Carole Jackson arriving on a TAA flight, Mascot","primoId":"ADLIB110062563","slug":"adlib110062563","shortcode":"","imageUrl":"https:\/\/dxlab.sl.nsw.gov.au\/images-newselfwales\/d7_17928.jpg","content":"beauty contestants, headgear, portraits, Kingsford-Smith Airport (Sydney, N.S.W.), Adult Females","imageType":"portrait","date":"2018-05-15 01:05:28","dateText":"20 Nov 1964","timestamp":"","instagramUsername":"","featuredMedia":{"sourceUrl":"https:\/\/dxlab.sl.nsw.gov.au\/images-newselfwales\/d7_17928.jpg","sizes":{"medium":{"sourceUrl":"https:\/\/dxlab.sl.nsw.gov.au\/images-newselfwales\/d7_17928-300x297.jpg","width":300,"height":297,"__typename":"MediaSize"},"full":{"sourceUrl":"https:\/\/dxlab.sl.nsw.gov.au\/images-newselfwales\/d7_17928.jpg","width":1938,"height":1920,"__typename":"MediaSize"},"__typename":"MediaSizes"},"__typename":"Media"},"__typename":"NewSelfWalesPortrait"},{"id":66080,"title":"Nos. 821-918: Photographic prints of missionaries and Indigenous people in the Northern Territory, ca. 1885-1938","primoId":"ADLIB110373145","slug":"adlib110373145-fl821785","shortcode":"","imageUrl":"https:\/\/dxlab.sl.nsw.gov.au\/images-newselfwales\/selfie-1535620676875-.jpg","content":"Goulburn Islands (N.T.), Milingimbi Island (N.T.), Thursday Island (Qld.), Northern Territory, Aboriginal Australians--Northern Territory--Social life and customs., Aboriginal Australians--Photographs.","imageType":"portrait","date":"2018-09-04 09:26:34","dateText":"ca. 1885-1938","timestamp":"","instagramUsername":"","featuredMedia":{"sourceUrl":"https:\/\/dxlab.sl.nsw.gov.au\/images-newselfwales\/selfie-1535620676875-.jpg","sizes":{"medium":{"sourceUrl":"https:\/\/dxlab.sl.nsw.gov.au\/images-newselfwales\/selfie-1535620676875--228x300.jpg","width":228,"height":300,"__typename":"MediaSize"},"full":{"sourceUrl":"https:\/\/dxlab.sl.nsw.gov.au\/images-newselfwales\/selfie-1535620676875-.jpg","width":799,"height":1050,"__typename":"MediaSize"},"__typename":"MediaSizes"},"__typename":"Media"},"__typename":"NewSelfWalesPortrait"},{"id":54772,"title":"Charles Kingsford-Smith and Charles Ulm, on landing after the Pacific flight, Mascot, 10 June 1928 \/ unknown photographer","primoId":"ADLIB110326723","slug":"adlib110326723","shortcode":"","imageUrl":"https:\/\/dxlab.sl.nsw.gov.au\/images-newselfwales\/selfie1526350482287.jpg","content":"aviators, portraits, protective clothing, record-breakers, signatures, Mascot (N.S.W.), Adult Males","imageType":"portrait","date":"2018-05-15 02:14:42","dateText":"10 June 1928","timestamp":"","instagramUsername":"","featuredMedia":{"sourceUrl":"https:\/\/dxlab.sl.nsw.gov.au\/images-newselfwales\/selfie1526350482287.jpg","sizes":{"medium":{"sourceUrl":"https:\/\/dxlab.sl.nsw.gov.au\/images-newselfwales\/selfie1526350482287-300x230.jpg","width":300,"height":230,"__typename":"MediaSize"},"full":{"sourceUrl":"https:\/\/dxlab.sl.nsw.gov.au\/images-newselfwales\/selfie1526350482287.jpg","width":1400,"height":1073,"__typename":"MediaSize"},"__typename":"MediaSizes"},"__typename":"Media"},"__typename":"NewSelfWalesPortrait"},{"id":22257,"title":"Charles Kenningham \/ The Falk Studios, 496 George Street, Sydney, June 1899","primoId":"ADLIB110324353","slug":"adlib110324353","shortcode":"","imageUrl":"https:\/\/dxlab.sl.nsw.gov.au\/images-newselfwales\/selfie1525065854796.jpg","content":"singers, portraits, Adult Males","imageType":"portrait","date":"2018-04-30 05:24:14","dateText":"June 1899","timestamp":"","instagramUsername":"","featuredMedia":{"sourceUrl":"https:\/\/dxlab.sl.nsw.gov.au\/images-newselfwales\/selfie1525065854796.jpg","sizes":{"medium":{"sourceUrl":"https:\/\/dxlab.sl.nsw.gov.au\/images-newselfwales\/selfie1525065854796-208x300.jpg","width":208,"height":300,"__typename":"MediaSize"},"full":{"sourceUrl":"https:\/\/dxlab.sl.nsw.gov.au\/images-newselfwales\/selfie1525065854796.jpg","width":728,"height":1050,"__typename":"MediaSize"},"__typename":"MediaSizes"},"__typename":"Media"},"__typename":"NewSelfWalesPortrait"},{"id":44667,"title":"Henry Smithers Hayes of the Brisbane Mill, Parramatta Road, 1845 \/ painted by Joseph T. Dennis","primoId":"ADLIB110321283","slug":"adlib110321283","shortcode":"","imageUrl":"https:\/\/dxlab.sl.nsw.gov.au\/images-newselfwales\/selfie1525848359555.jpg","content":"interiors, businesspeople, portraits, Adult Males","imageType":"portrait","date":"2018-05-09 06:45:59","dateText":"1845","timestamp":"","instagramUsername":"","featuredMedia":{"sourceUrl":"https:\/\/dxlab.sl.nsw.gov.au\/images-newselfwales\/selfie1525848359555.jpg","sizes":{"medium":{"sourceUrl":"https:\/\/dxlab.sl.nsw.gov.au\/images-newselfwales\/selfie1525848359555-e1537944186450-229x300.jpg","width":229,"height":300,"__typename":"MediaSize"},"full":{"sourceUrl":"https:\/\/dxlab.sl.nsw.gov.au\/images-newselfwales\/selfie1525848359555.jpg","width":766,"height":1002,"__typename":"MediaSize"},"__typename":"MediaSizes"},"__typename":"Media"},"__typename":"NewSelfWalesPortrait"},{"id":46911,"title":"Mr &amp; Mrs Smith","primoId":"ADLIB110042166","slug":"adlib110042166","shortcode":"","imageUrl":"https:\/\/dxlab.sl.nsw.gov.au\/images-newselfwales\/selfie1525857624942.jpg","content":"interiors, couples, portraits, Adult Females, Adult Males","imageType":"portrait","date":"2018-05-09 09:20:25","dateText":"1870-1875","timestamp":"","instagramUsername":"","featuredMedia":{"sourceUrl":"https:\/\/dxlab.sl.nsw.gov.au\/images-newselfwales\/selfie1525857624942.jpg","sizes":{"medium":{"sourceUrl":"https:\/\/dxlab.sl.nsw.gov.au\/images-newselfwales\/selfie1525857624942-228x300.jpg","width":228,"height":300,"__typename":"MediaSize"},"full":{"sourceUrl":"https:\/\/dxlab.sl.nsw.gov.au\/images-newselfwales\/selfie1525857624942.jpg","width":798,"height":1050,"__typename":"MediaSize"},"__typename":"MediaSizes"},"__typename":"Media"},"__typename":"NewSelfWalesPortrait"},{"id":56438,"title":"Studio portrait of Dianne Dorgan for TV Times issue 22 July 1964","primoId":"ADLIB110061135","slug":"adlib110061135","shortcode":"","imageUrl":"https:\/\/dxlab.sl.nsw.gov.au\/images-newselfwales\/d7_16544.jpg","content":"interiors, portraits, television personalities, Australian Photographic Agency (42 Pitt Street, Sydney, N.S.W.), Adult Females","imageType":"portrait","date":"2018-05-15 09:48:23","dateText":"11 Jun 1964","timestamp":"","instagramUsername":"","featuredMedia":{"sourceUrl":"https:\/\/dxlab.sl.nsw.gov.au\/images-newselfwales\/d7_16544.jpg","sizes":{"medium":{"sourceUrl":"https:\/\/dxlab.sl.nsw.gov.au\/images-newselfwales\/d7_16544-238x300.jpg","width":238,"height":300,"__typename":"MediaSize"},"full":{"sourceUrl":"https:\/\/dxlab.sl.nsw.gov.au\/images-newselfwales\/d7_16544.jpg","width":1476,"height":1862,"__typename":"MediaSize"},"__typename":"MediaSizes"},"__typename":"Media"},"__typename":"NewSelfWalesPortrait"},{"id":61898,"title":"c h r i s","primoId":"","slug":"","shortcode":"Bl3tcefAG5T","imageUrl":"https:\/\/dxlab.sl.nsw.gov.au\/images-newselfwales\/selfie-1534063393322-.jpg","content":"Stoked to announce that new album is dropping next month.\n\ud83d\udce2\ud83d\udd18\ud83e\udd19\ud83c\udffc\n\u2018Like Child\u2019s Play (Comme un jeu d\u2019enfant)\u2019 2018, Daniel Buren\n\ud83d\udcf7 @feliciagnes\n.\n.\n.\n@carriageworks #danielburen #likechildsplay #commeunjeudenfant #carriageworks #sydney #ilovesydney #sydneylocal #sydneyart #timeoutsydney #broadsheetsydney #newsouthwales #newselfwales #australia #seeaustralia","imageType":"instagram_selfie","date":"2018-08-15 09:41:08","dateText":"","timestamp":1532985190,"instagramUsername":"christianocious","featuredMedia":{"sourceUrl":"https:\/\/dxlab.sl.nsw.gov.au\/images-newselfwales\/selfie-1534063393322-.jpg","sizes":{"medium":{"sourceUrl":"https:\/\/dxlab.sl.nsw.gov.au\/images-newselfwales\/selfie-1534063393322--300x300.jpg","width":300,"height":300,"__typename":"MediaSize"},"full":{"sourceUrl":"https:\/\/dxlab.sl.nsw.gov.au\/images-newselfwales\/selfie-1534063393322-.jpg","width":1080,"height":1080,"__typename":"MediaSize"},"__typename":"MediaSizes"},"__typename":"Media"},"__typename":"NewSelfWalesInstagramSelfie"},{"id":64549,"title":"Zoe","primoId":"","slug":"","shortcode":"BkMm6dYBE0J","imageUrl":"https:\/\/dxlab.sl.nsw.gov.au\/images-newselfwales\/selfie-1535319244432-.jpg","content":"Coffee number 3!!! #wheninmelbourne never made it past 2 before so this\u2019ll be interesting! Doubt I\u2019ll be sleeping tonight \ud83d\ude33\ud83d\ude33\ud83d\ude33 #coffee #addict #newselfwales","imageType":"instagram_selfie","date":"2018-08-31 15:16:36","dateText":"","timestamp":1529391441,"instagramUsername":"zoe_for_life88","featuredMedia":{"sourceUrl":"https:\/\/dxlab.sl.nsw.gov.au\/images-newselfwales\/selfie-1535319244432-.jpg","sizes":{"medium":{"sourceUrl":"https:\/\/dxlab.sl.nsw.gov.au\/images-newselfwales\/selfie-1535319244432--300x225.jpg","width":300,"height":225,"__typename":"MediaSize"},"full":{"sourceUrl":"https:\/\/dxlab.sl.nsw.gov.au\/images-newselfwales\/selfie-1535319244432-.jpg","width":1080,"height":810,"__typename":"MediaSize"},"__typename":"MediaSizes"},"__typename":"Media"},"__typename":"NewSelfWalesInstagramSelfie"},{"id":106758,"title":"Haixi tan","primoId":"","slug":"","shortcode":"BtFfv1JFuBG","imageUrl":"https:\/\/dxlab.sl.nsw.gov.au\/images-newselfwales\/selfie-1548480604675-.jpg","content":"#newselfwales","imageType":"instagram_selfie","date":"2019-01-26 17:06:08","dateText":"","timestamp":1548480156,"instagramUsername":"melodyxiaoxi2018","featuredMedia":{"sourceUrl":"https:\/\/dxlab.sl.nsw.gov.au\/images-newselfwales\/selfie-1548480604675-.jpg","sizes":{"medium":{"sourceUrl":"https:\/\/dxlab.sl.nsw.gov.au\/images-newselfwales\/selfie-1548480604675--300x300.jpg","width":300,"height":300,"__typename":"MediaSize"},"full":{"sourceUrl":"https:\/\/dxlab.sl.nsw.gov.au\/images-newselfwales\/selfie-1548480604675-.jpg","width":1080,"height":1080,"__typename":"MediaSize"},"__typename":"MediaSizes"},"__typename":"Media"},"__typename":"NewSelfWalesInstagramSelfie"},{"id":77809,"title":"Julie","primoId":"","slug":"","shortcode":"Boziqc1HFKC","imageUrl":"https:\/\/dxlab.sl.nsw.gov.au\/images-newselfwales\/selfie-1539288003717-.jpg","content":"Beanie weather is still here! \ud83c\udf2b\n.\n.\n.\n.\n.\n.\n.\n.\n#newselfwales #hathair #beanieweather #tgif","imageType":"instagram_selfie","date":"2018-10-12 08:55:06","dateText":"","timestamp":1539287770,"instagramUsername":"jujy.94","featuredMedia":{"sourceUrl":"https:\/\/dxlab.sl.nsw.gov.au\/images-newselfwales\/selfie-1539288003717-.jpg","sizes":{"medium":{"sourceUrl":"https:\/\/dxlab.sl.nsw.gov.au\/images-newselfwales\/selfie-1539288003717--240x300.jpg","width":240,"height":300,"__typename":"MediaSize"},"full":{"sourceUrl":"https:\/\/dxlab.sl.nsw.gov.au\/images-newselfwales\/selfie-1539288003717-.jpg","width":1080,"height":1350,"__typename":"MediaSize"},"__typename":"MediaSizes"},"__typename":"Media"},"__typename":"NewSelfWalesInstagramSelfie"},{"id":107408,"title":"tracie and sylvia","primoId":"","slug":"","shortcode":"","imageUrl":"https:\/\/dxlab.sl.nsw.gov.au\/images-newselfwales\/selfie-1548733369611.png","content":"tracie and sylvia","imageType":"gallery_selfie","date":"2019-01-29 14:42:49","dateText":"","timestamp":"","instagramUsername":"","featuredMedia":{"sourceUrl":"https:\/\/dxlab.sl.nsw.gov.au\/images-newselfwales\/selfie-1548733369611.png","sizes":{"medium":{"sourceUrl":"https:\/\/dxlab.sl.nsw.gov.au\/images-newselfwales\/selfie-1548733369611-300x300.png","width":300,"height":300,"__typename":"MediaSize"},"full":{"sourceUrl":"https:\/\/dxlab.sl.nsw.gov.au\/images-newselfwales\/selfie-1548733369611.png","width":1080,"height":1080,"__typename":"MediaSize"},"__typename":"MediaSizes"},"__typename":"Media"},"__typename":"NewSelfWalesGallerySelfie"},{"id":110688,"title":"julie","primoId":"","slug":"","shortcode":"","imageUrl":"https:\/\/dxlab.sl.nsw.gov.au\/images-newselfwales\/selfie-1549929436527.png","content":"julie","imageType":"gallery_selfie","date":"2019-02-12 10:57:16","dateText":"","timestamp":"","instagramUsername":"","featuredMedia":{"sourceUrl":"https:\/\/dxlab.sl.nsw.gov.au\/images-newselfwales\/selfie-1549929436527.png","sizes":{"medium":{"sourceUrl":"https:\/\/dxlab.sl.nsw.gov.au\/images-newselfwales\/selfie-1549929436527-300x300.png","width":300,"height":300,"__typename":"MediaSize"},"full":{"sourceUrl":"https:\/\/dxlab.sl.nsw.gov.au\/images-newselfwales\/selfie-1549929436527.png","width":1080,"height":1080,"__typename":"MediaSize"},"__typename":"MediaSizes"},"__typename":"Media"},"__typename":"NewSelfWalesGallerySelfie"},{"id":77246,"title":"`Lily Taylor","primoId":"","slug":"","shortcode":"","imageUrl":"https:\/\/dxlab.sl.nsw.gov.au\/images-newselfwales\/selfie-1539145256410.png","content":"`Lily Taylor","imageType":"gallery_selfie","date":"2018-10-10 14:20:56","dateText":"","timestamp":"","instagramUsername":"","featuredMedia":{"sourceUrl":"https:\/\/dxlab.sl.nsw.gov.au\/images-newselfwales\/selfie-1539145256410.png","sizes":{"medium":{"sourceUrl":"https:\/\/dxlab.sl.nsw.gov.au\/images-newselfwales\/selfie-1539145256410-300x300.png","width":300,"height":300,"__typename":"MediaSize"},"full":{"sourceUrl":"https:\/\/dxlab.sl.nsw.gov.au\/images-newselfwales\/selfie-1539145256410.png","width":1080,"height":1080,"__typename":"MediaSize"},"__typename":"MediaSizes"},"__typename":"Media"},"__typename":"NewSelfWalesGallerySelfie"},{"id":84524,"title":"Noora","primoId":"","slug":"","shortcode":"","imageUrl":"https:\/\/dxlab.sl.nsw.gov.au\/images-newselfwales\/selfie-1541301050867.png","content":"Noora","imageType":"gallery_selfie","date":"2018-11-04 14:10:50","dateText":"","timestamp":"","instagramUsername":"","featuredMedia":{"sourceUrl":"https:\/\/dxlab.sl.nsw.gov.au\/images-newselfwales\/selfie-1541301050867.png","sizes":{"medium":{"sourceUrl":"https:\/\/dxlab.sl.nsw.gov.au\/images-newselfwales\/selfie-1541301050867-300x300.png","width":300,"height":300,"__typename":"MediaSize"},"full":{"sourceUrl":"https:\/\/dxlab.sl.nsw.gov.au\/images-newselfwales\/selfie-1541301050867.png","width":1080,"height":1080,"__typename":"MediaSize"},"__typename":"MediaSizes"},"__typename":"Media"},"__typename":"NewSelfWalesGallerySelfie"}]}