{"data":[{"id":16114,"title":"Miss A. [Ada ?] M. Stevens, [age 5 in 1873, daughter of Walter and Elizabeth, nee Stanley ?]","primoId":"ADLIB110042090","slug":"adlib110042090","shortcode":"","imageUrl":"https:\/\/dxlab.sl.nsw.gov.au\/images-newselfwales\/selfie1524038266393.jpg","content":"interiors, portraits, girls","imageType":"portrait","date":"2018-04-18 07:57:46","dateText":"1870-1875","timestamp":"","instagramUsername":"","featuredMedia":{"sourceUrl":"https:\/\/dxlab.sl.nsw.gov.au\/images-newselfwales\/selfie1524038266393.jpg","sizes":{"medium":{"sourceUrl":"https:\/\/dxlab.sl.nsw.gov.au\/images-newselfwales\/selfie1524038266393-222x300.jpg","width":222,"height":300,"__typename":"MediaSize"},"full":{"sourceUrl":"https:\/\/dxlab.sl.nsw.gov.au\/images-newselfwales\/selfie1524038266393.jpg","width":776,"height":1050,"__typename":"MediaSize"},"__typename":"MediaSizes"},"__typename":"Media"},"__typename":"NewSelfWalesPortrait"},{"id":50491,"title":"Anna Pavlova and male partner in unidentified ballet \/ photographer Becker &amp; Maass, Berlin W.9, ca. 1926","primoId":"ADLIB110326145","slug":"adlib110326145","shortcode":"","imageUrl":"https:\/\/dxlab.sl.nsw.gov.au\/images-newselfwales\/selfie1525930284551.jpg","content":"ballet, ballet dancers, portraits, theatrical costumes, Adult Females, Adult Males","imageType":"portrait","date":"2018-05-10 05:31:24","dateText":"ca. 1926","timestamp":"","instagramUsername":"","featuredMedia":{"sourceUrl":"https:\/\/dxlab.sl.nsw.gov.au\/images-newselfwales\/selfie1525930284551.jpg","sizes":{"medium":{"sourceUrl":"https:\/\/dxlab.sl.nsw.gov.au\/images-newselfwales\/selfie1525930284551-e1537842010381-225x300.jpg","width":225,"height":300,"__typename":"MediaSize"},"full":{"sourceUrl":"https:\/\/dxlab.sl.nsw.gov.au\/images-newselfwales\/selfie1525930284551.jpg","width":756,"height":1008,"__typename":"MediaSize"},"__typename":"MediaSizes"},"__typename":"Media"},"__typename":"NewSelfWalesPortrait"},{"id":52594,"title":"Cottage and woman, Hill End","primoId":"ADLIB110040684","slug":"adlib110040684","shortcode":"","imageUrl":"https:\/\/dxlab.sl.nsw.gov.au\/images-newselfwales\/selfie1525940727371.jpg","content":"bark roofs, historic buildings, houses, portraits, Hill End (N.S.W.), Adult Females","imageType":"portrait","date":"2018-05-10 08:25:27","dateText":"1870-1875","timestamp":"","instagramUsername":"","featuredMedia":{"sourceUrl":"https:\/\/dxlab.sl.nsw.gov.au\/images-newselfwales\/selfie1525940727371.jpg","sizes":{"medium":{"sourceUrl":"https:\/\/dxlab.sl.nsw.gov.au\/images-newselfwales\/selfie1525940727371-300x226.jpg","width":300,"height":226,"__typename":"MediaSize"},"full":{"sourceUrl":"https:\/\/dxlab.sl.nsw.gov.au\/images-newselfwales\/selfie1525940727371.jpg","width":1400,"height":1053,"__typename":"MediaSize"},"__typename":"MediaSizes"},"__typename":"Media"},"__typename":"NewSelfWalesPortrait"},{"id":67079,"title":"Photographic scenes &amp; portraits of Fijian natives, Aborigines of Queensland and Clarence River NSW, British Royalty and the Exhibition Building at Prince Alfred Park, 1870 - 1875","primoId":"ADLIB110317436","slug":"adlib110317436-fl1112871","shortcode":"","imageUrl":"https:\/\/dxlab.sl.nsw.gov.au\/images-newselfwales\/selfie-1535681480139-.jpg","content":"interiors, Aboriginal peoples (Australians), buildings, structures &amp; establishments, coasts, exhibition halls, Fijians, islands, photographic studios, portraits, royal family (Fiji), royal family (Great Britain), Clarence River Region (N.S.W.), Exhibition Building (Prince Alfred Park, N.S.W.), Fiji, Queensland, Adult Males, Adult Females, girls, boys","imageType":"portrait","date":"2018-09-03 15:08:22","dateText":"1870-1875","timestamp":"","instagramUsername":"","featuredMedia":{"sourceUrl":"https:\/\/dxlab.sl.nsw.gov.au\/images-newselfwales\/selfie-1535681480139-.jpg","sizes":{"medium":{"sourceUrl":"https:\/\/dxlab.sl.nsw.gov.au\/images-newselfwales\/selfie-1535681480139--190x300.jpg","width":190,"height":300,"__typename":"MediaSize"},"full":{"sourceUrl":"https:\/\/dxlab.sl.nsw.gov.au\/images-newselfwales\/selfie-1535681480139-.jpg","width":665,"height":1050,"__typename":"MediaSize"},"__typename":"MediaSizes"},"__typename":"Media"},"__typename":"NewSelfWalesPortrait"},{"id":56260,"title":"Conference of master printers (or movie picture distributors ?)","primoId":"ADLIB110006784","slug":"adlib110006784","shortcode":"","imageUrl":"https:\/\/dxlab.sl.nsw.gov.au\/images-newselfwales\/selfie1526376873817.jpg","content":"conventions, film distributors, portraits, printers (people), Coogee Bay Hotel (Coogee, N.S.W.), Adult Males","imageType":"portrait","date":"2018-05-15 09:34:33","dateText":"September 1943","timestamp":"","instagramUsername":"","featuredMedia":{"sourceUrl":"https:\/\/dxlab.sl.nsw.gov.au\/images-newselfwales\/selfie1526376873817.jpg","sizes":{"medium":{"sourceUrl":"https:\/\/dxlab.sl.nsw.gov.au\/images-newselfwales\/selfie1526376873817-e1534816865749-300x228.jpg","width":300,"height":228,"__typename":"MediaSize"},"full":{"sourceUrl":"https:\/\/dxlab.sl.nsw.gov.au\/images-newselfwales\/selfie1526376873817.jpg","width":1305,"height":990,"__typename":"MediaSize"},"__typename":"MediaSizes"},"__typename":"Media"},"__typename":"NewSelfWalesPortrait"},{"id":12925,"title":"Nelson Moore Richardson, of Montevideo, W. Weymouth, England, 1915-1925","primoId":"ADLIB110332597","slug":"adlib110332597","shortcode":"","imageUrl":"https:\/\/dxlab.sl.nsw.gov.au\/images-newselfwales\/selfie1524026016554.jpg","content":"portraits","imageType":"portrait","date":"2018-04-18 04:33:36","dateText":"probably between 1915-1925","timestamp":"","instagramUsername":"","featuredMedia":{"sourceUrl":"https:\/\/dxlab.sl.nsw.gov.au\/images-newselfwales\/selfie1524026016554.jpg","sizes":{"medium":{"sourceUrl":"https:\/\/dxlab.sl.nsw.gov.au\/images-newselfwales\/selfie1524026016554-194x300.jpg","width":194,"height":300,"__typename":"MediaSize"},"full":{"sourceUrl":"https:\/\/dxlab.sl.nsw.gov.au\/images-newselfwales\/selfie1524026016554.jpg","width":678,"height":1050,"__typename":"MediaSize"},"__typename":"MediaSizes"},"__typename":"Media"},"__typename":"NewSelfWalesPortrait"},{"id":35948,"title":"Miss Taylor","primoId":"ADLIB110042048","slug":"adlib110042048","shortcode":"","imageUrl":"https:\/\/dxlab.sl.nsw.gov.au\/images-newselfwales\/selfie1525671348475.jpg","content":"interiors, portraits, Adult Females","imageType":"portrait","date":"2018-05-07 05:35:48","dateText":"1870-1875","timestamp":"","instagramUsername":"","featuredMedia":{"sourceUrl":"https:\/\/dxlab.sl.nsw.gov.au\/images-newselfwales\/selfie1525671348475.jpg","sizes":{"medium":{"sourceUrl":"https:\/\/dxlab.sl.nsw.gov.au\/images-newselfwales\/selfie1525671348475-225x300.jpg","width":225,"height":300,"__typename":"MediaSize"},"full":{"sourceUrl":"https:\/\/dxlab.sl.nsw.gov.au\/images-newselfwales\/selfie1525671348475.jpg","width":789,"height":1050,"__typename":"MediaSize"},"__typename":"MediaSizes"},"__typename":"Media"},"__typename":"NewSelfWalesPortrait"},{"id":44975,"title":"Mrs Pagg [Pegg ?] and baby","primoId":"ADLIB110043122","slug":"adlib110043122","shortcode":"","imageUrl":"https:\/\/dxlab.sl.nsw.gov.au\/images-newselfwales\/selfie1525849725757.jpg","content":"interiors, portraits, Adult Females, babies","imageType":"portrait","date":"2018-05-09 07:08:45","dateText":"1870-1875","timestamp":"","instagramUsername":"","featuredMedia":{"sourceUrl":"https:\/\/dxlab.sl.nsw.gov.au\/images-newselfwales\/selfie1525849725757.jpg","sizes":{"medium":{"sourceUrl":"https:\/\/dxlab.sl.nsw.gov.au\/images-newselfwales\/selfie1525849725757-223x300.jpg","width":223,"height":300,"__typename":"MediaSize"},"full":{"sourceUrl":"https:\/\/dxlab.sl.nsw.gov.au\/images-newselfwales\/selfie1525849725757.jpg","width":779,"height":1050,"__typename":"MediaSize"},"__typename":"MediaSizes"},"__typename":"Media"},"__typename":"NewSelfWalesPortrait"},{"id":13151,"title":"Ancestral portrait of Quong Tart's mother, ca. 1888","primoId":"ADLIB110325886","slug":"adlib110325886","shortcode":"","imageUrl":"https:\/\/dxlab.sl.nsw.gov.au\/images-newselfwales\/selfie1524027041451.jpg","content":"Chinese peoples, mothers, official dress, portraits, Adult Females","imageType":"portrait","date":"2018-04-18 04:50:41","dateText":"ca. 1888","timestamp":"","instagramUsername":"","featuredMedia":{"sourceUrl":"https:\/\/dxlab.sl.nsw.gov.au\/images-newselfwales\/selfie1524027041451.jpg","sizes":{"medium":{"sourceUrl":"https:\/\/dxlab.sl.nsw.gov.au\/images-newselfwales\/selfie1524027041451-e1537335938864-235x300.jpg","width":235,"height":300,"__typename":"MediaSize"},"full":{"sourceUrl":"https:\/\/dxlab.sl.nsw.gov.au\/images-newselfwales\/selfie1524027041451.jpg","width":784,"height":1000,"__typename":"MediaSize"},"__typename":"MediaSizes"},"__typename":"Media"},"__typename":"NewSelfWalesPortrait"},{"id":67183,"title":"Sydney Town street portraits, March 2014-August 2015 \/ photographs by Jon Lewis","primoId":"ADLIB110581269","slug":"adlib110581269-fl3811146","shortcode":"","imageUrl":"https:\/\/dxlab.sl.nsw.gov.au\/images-newselfwales\/selfie-1535681553767-.jpg","content":"portraits, Sydney (N.S.W.), Portrait photography--New South Wales--21st century., Street photography--New South Wales--Sydney, Aboriginal Australians--New South Wales--Portraits","imageType":"portrait","date":"2018-09-03 14:16:12","dateText":"March 2014-August 2015","timestamp":"","instagramUsername":"","featuredMedia":{"sourceUrl":"https:\/\/dxlab.sl.nsw.gov.au\/images-newselfwales\/selfie-1535681553767-.jpg","sizes":{"medium":{"sourceUrl":"https:\/\/dxlab.sl.nsw.gov.au\/images-newselfwales\/selfie-1535681553767--300x200.jpg","width":300,"height":200,"__typename":"MediaSize"},"full":{"sourceUrl":"https:\/\/dxlab.sl.nsw.gov.au\/images-newselfwales\/selfie-1535681553767-.jpg","width":500,"height":333,"__typename":"MediaSize"},"__typename":"MediaSizes"},"__typename":"Media"},"__typename":"NewSelfWalesPortrait"},{"id":16666,"title":"Portrait of Miss Humphreys","primoId":"ADLIB110094325","slug":"adlib110094325","shortcode":"","imageUrl":"https:\/\/dxlab.sl.nsw.gov.au\/images-newselfwales\/selfie1524040566395.jpg","content":"portraits, Adult Females","imageType":"portrait","date":"2018-04-18 08:36:06","dateText":"1870-1875","timestamp":"","instagramUsername":"","featuredMedia":{"sourceUrl":"https:\/\/dxlab.sl.nsw.gov.au\/images-newselfwales\/selfie1524040566395.jpg","sizes":{"medium":{"sourceUrl":"https:\/\/dxlab.sl.nsw.gov.au\/images-newselfwales\/selfie1524040566395-223x300.jpg","width":223,"height":300,"__typename":"MediaSize"},"full":{"sourceUrl":"https:\/\/dxlab.sl.nsw.gov.au\/images-newselfwales\/selfie1524040566395.jpg","width":780,"height":1050,"__typename":"MediaSize"},"__typename":"MediaSizes"},"__typename":"Media"},"__typename":"NewSelfWalesPortrait"},{"id":44011,"title":"Capt. James Lord Wilkinson, of the ship Fairy Rock, ca. 1870 \/ photographer Francis W. Robinson, George Street, Sydney","primoId":"ADLIB110350595","slug":"adlib110350595","shortcode":"","imageUrl":"https:\/\/dxlab.sl.nsw.gov.au\/images-newselfwales\/selfie1525838940378.jpg","content":"portraits, ships' captains, Adult Males","imageType":"portrait","date":"2018-05-09 04:09:00","dateText":"ca. 1870","timestamp":"","instagramUsername":"","featuredMedia":{"sourceUrl":"https:\/\/dxlab.sl.nsw.gov.au\/images-newselfwales\/selfie1525838940378.jpg","sizes":{"medium":{"sourceUrl":"https:\/\/dxlab.sl.nsw.gov.au\/images-newselfwales\/selfie1525838940378-192x300.jpg","width":192,"height":300,"__typename":"MediaSize"},"full":{"sourceUrl":"https:\/\/dxlab.sl.nsw.gov.au\/images-newselfwales\/selfie1525838940378.jpg","width":673,"height":1050,"__typename":"MediaSize"},"__typename":"MediaSizes"},"__typename":"Media"},"__typename":"NewSelfWalesPortrait"},{"id":60981,"title":"The Hound Lounge","primoId":"","slug":"","shortcode":"BkQ_hN4BVuS","imageUrl":"https:\/\/dxlab.sl.nsw.gov.au\/images-newselfwales\/selfie1530757395209.jpg","content":"June 21st is national selfie day in America. We thought we\u2019d kick it off a bit early here. We think we nailed it. #nationalselfieday #bordercollie #boxer #cavoodle #dogdaycare #dogsofsydney #doggydaycare #innerwest #selfie #minipoodle #newselfwales","imageType":"instagram_selfie","date":"2018-09-03 09:23:47","dateText":"","timestamp":1529538564,"instagramUsername":"the_hound_lounge","featuredMedia":{"sourceUrl":"https:\/\/dxlab.sl.nsw.gov.au\/images-newselfwales\/selfie1530757395209.jpg","sizes":{"medium":{"sourceUrl":"https:\/\/dxlab.sl.nsw.gov.au\/images-newselfwales\/selfie1530757395209-300x300.jpg","width":300,"height":300,"__typename":"MediaSize"},"full":{"sourceUrl":"https:\/\/dxlab.sl.nsw.gov.au\/images-newselfwales\/selfie1530757395209.jpg","width":1080,"height":1080,"__typename":"MediaSize"},"__typename":"MediaSizes"},"__typename":"Media"},"__typename":"NewSelfWalesInstagramSelfie"},{"id":78150,"title":"Basim M Alansari","primoId":"","slug":"","shortcode":"Bo1nMeagafT","imageUrl":"https:\/\/dxlab.sl.nsw.gov.au\/images-newselfwales\/selfie-1539359403930-.jpg","content":"#newselfwales","imageType":"instagram_selfie","date":"2018-10-15 09:40:02","dateText":"","timestamp":1539357255,"instagramUsername":"mbalansari","featuredMedia":{"sourceUrl":"https:\/\/dxlab.sl.nsw.gov.au\/images-newselfwales\/selfie-1539359403930-.jpg","sizes":{"medium":{"sourceUrl":"https:\/\/dxlab.sl.nsw.gov.au\/images-newselfwales\/selfie-1539359403930--300x300.jpg","width":300,"height":300,"__typename":"MediaSize"},"full":{"sourceUrl":"https:\/\/dxlab.sl.nsw.gov.au\/images-newselfwales\/selfie-1539359403930-.jpg","width":1080,"height":1080,"__typename":"MediaSize"},"__typename":"MediaSizes"},"__typename":"Media"},"__typename":"NewSelfWalesInstagramSelfie"},{"id":73555,"title":"Emma\u2019s Beauty Inspirations","primoId":"","slug":"","shortcode":"BoQddusnryk","imageUrl":"https:\/\/dxlab.sl.nsw.gov.au\/images-newselfwales\/selfie-1538110803614-.jpg","content":"#newselfwales","imageType":"instagram_selfie","date":"2018-10-02 11:59:52","dateText":"","timestamp":1538110639,"instagramUsername":"emmasbeautyinspirations","featuredMedia":{"sourceUrl":"https:\/\/dxlab.sl.nsw.gov.au\/images-newselfwales\/selfie-1538110803614-.jpg","sizes":{"medium":{"sourceUrl":"https:\/\/dxlab.sl.nsw.gov.au\/images-newselfwales\/selfie-1538110803614--300x300.jpg","width":300,"height":300,"__typename":"MediaSize"},"full":{"sourceUrl":"https:\/\/dxlab.sl.nsw.gov.au\/images-newselfwales\/selfie-1538110803614-.jpg","width":960,"height":960,"__typename":"MediaSize"},"__typename":"MediaSizes"},"__typename":"Media"},"__typename":"NewSelfWalesInstagramSelfie"},{"id":62323,"title":"AnnieFF","primoId":"","slug":"","shortcode":"BmdW7AmDT6H","imageUrl":"https:\/\/dxlab.sl.nsw.gov.au\/images-newselfwales\/selfie-1534248604973-.jpg","content":"#newselfwales","imageType":"instagram_selfie","date":"2018-08-15 09:41:07","dateText":"","timestamp":1534248450,"instagramUsername":"annieff197","featuredMedia":{"sourceUrl":"https:\/\/dxlab.sl.nsw.gov.au\/images-newselfwales\/selfie-1534248604973-.jpg","sizes":{"medium":{"sourceUrl":"https:\/\/dxlab.sl.nsw.gov.au\/images-newselfwales\/selfie-1534248604973--240x300.jpg","width":240,"height":300,"__typename":"MediaSize"},"full":{"sourceUrl":"https:\/\/dxlab.sl.nsw.gov.au\/images-newselfwales\/selfie-1534248604973-.jpg","width":1080,"height":1350,"__typename":"MediaSize"},"__typename":"MediaSizes"},"__typename":"Media"},"__typename":"NewSelfWalesInstagramSelfie"},{"id":111571,"title":"h","primoId":"","slug":"","shortcode":"","imageUrl":"https:\/\/dxlab.sl.nsw.gov.au\/images-newselfwales\/selfie-1550207335288.png","content":"h","imageType":"gallery_selfie","date":"2019-02-15 16:08:55","dateText":"","timestamp":"","instagramUsername":"","featuredMedia":{"sourceUrl":"https:\/\/dxlab.sl.nsw.gov.au\/images-newselfwales\/selfie-1550207335288.png","sizes":{"medium":{"sourceUrl":"https:\/\/dxlab.sl.nsw.gov.au\/images-newselfwales\/selfie-1550207335288-300x300.png","width":300,"height":300,"__typename":"MediaSize"},"full":{"sourceUrl":"https:\/\/dxlab.sl.nsw.gov.au\/images-newselfwales\/selfie-1550207335288.png","width":1080,"height":1080,"__typename":"MediaSize"},"__typename":"MediaSizes"},"__typename":"Media"},"__typename":"NewSelfWalesGallerySelfie"},{"id":89303,"title":"caroline","primoId":"","slug":"","shortcode":"","imageUrl":"https:\/\/dxlab.sl.nsw.gov.au\/images-newselfwales\/selfie-1542858101554.png","content":"caroline","imageType":"gallery_selfie","date":"2018-11-22 14:41:41","dateText":"","timestamp":"","instagramUsername":"","featuredMedia":{"sourceUrl":"https:\/\/dxlab.sl.nsw.gov.au\/images-newselfwales\/selfie-1542858101554.png","sizes":{"medium":{"sourceUrl":"https:\/\/dxlab.sl.nsw.gov.au\/images-newselfwales\/selfie-1542858101554-300x300.png","width":300,"height":300,"__typename":"MediaSize"},"full":{"sourceUrl":"https:\/\/dxlab.sl.nsw.gov.au\/images-newselfwales\/selfie-1542858101554.png","width":1080,"height":1080,"__typename":"MediaSize"},"__typename":"MediaSizes"},"__typename":"Media"},"__typename":"NewSelfWalesGallerySelfie"},{"id":79538,"title":"carmel maloney","primoId":"","slug":"","shortcode":"","imageUrl":"https:\/\/dxlab.sl.nsw.gov.au\/images-newselfwales\/selfie-1539738318157.png","content":"carmel maloney","imageType":"gallery_selfie","date":"2018-10-17 11:05:18","dateText":"","timestamp":"","instagramUsername":"","featuredMedia":{"sourceUrl":"https:\/\/dxlab.sl.nsw.gov.au\/images-newselfwales\/selfie-1539738318157.png","sizes":{"medium":{"sourceUrl":"https:\/\/dxlab.sl.nsw.gov.au\/images-newselfwales\/selfie-1539738318157-300x300.png","width":300,"height":300,"__typename":"MediaSize"},"full":{"sourceUrl":"https:\/\/dxlab.sl.nsw.gov.au\/images-newselfwales\/selfie-1539738318157.png","width":1080,"height":1080,"__typename":"MediaSize"},"__typename":"MediaSizes"},"__typename":"Media"},"__typename":"NewSelfWalesGallerySelfie"},{"id":88798,"title":"Christa & Wayne _ Stanwell Park","primoId":"","slug":"","shortcode":"","imageUrl":"https:\/\/dxlab.sl.nsw.gov.au\/images-newselfwales\/selfie-1542677358411.png","content":"Christa & Wayne _ Stanwell Park","imageType":"gallery_selfie","date":"2018-11-20 12:29:18","dateText":"","timestamp":"","instagramUsername":"","featuredMedia":{"sourceUrl":"https:\/\/dxlab.sl.nsw.gov.au\/images-newselfwales\/selfie-1542677358411.png","sizes":{"medium":{"sourceUrl":"https:\/\/dxlab.sl.nsw.gov.au\/images-newselfwales\/selfie-1542677358411-300x300.png","width":300,"height":300,"__typename":"MediaSize"},"full":{"sourceUrl":"https:\/\/dxlab.sl.nsw.gov.au\/images-newselfwales\/selfie-1542677358411.png","width":1080,"height":1080,"__typename":"MediaSize"},"__typename":"MediaSizes"},"__typename":"Media"},"__typename":"NewSelfWalesGallerySelfie"}]}