{"data":[{"id":35640,"title":"Mary Gilmore , 1916 \/ photograph by May Moore","primoId":"ADLIB110343391","slug":"adlib110343391","shortcode":"","imageUrl":"https:\/\/dxlab.sl.nsw.gov.au\/images-newselfwales\/selfie1525670209918.jpg","content":"portraits, authors, Adult Females","imageType":"portrait","date":"2018-05-07 05:16:50","dateText":"1916","timestamp":"","instagramUsername":"","featuredMedia":{"sourceUrl":"https:\/\/dxlab.sl.nsw.gov.au\/images-newselfwales\/selfie1525670209918.jpg","sizes":{"medium":{"sourceUrl":"https:\/\/dxlab.sl.nsw.gov.au\/images-newselfwales\/selfie1525670209918-e1538004644261-229x300.jpg","width":229,"height":300,"__typename":"MediaSize"},"full":{"sourceUrl":"https:\/\/dxlab.sl.nsw.gov.au\/images-newselfwales\/selfie1525670209918.jpg","width":774,"height":1012,"__typename":"MediaSize"},"__typename":"MediaSizes"},"__typename":"Media"},"__typename":"NewSelfWalesPortrait"},{"id":29728,"title":"Mr Thomas Trivithie [Trevithick ?]","primoId":"ADLIB110042828","slug":"adlib110042828","shortcode":"","imageUrl":"https:\/\/dxlab.sl.nsw.gov.au\/images-newselfwales\/selfie1525330290118.jpg","content":"interiors, portraits, Adult Males","imageType":"portrait","date":"2018-05-03 06:51:29","dateText":"1870-1875","timestamp":"","instagramUsername":"","featuredMedia":{"sourceUrl":"https:\/\/dxlab.sl.nsw.gov.au\/images-newselfwales\/selfie1525330290118.jpg","sizes":{"medium":{"sourceUrl":"https:\/\/dxlab.sl.nsw.gov.au\/images-newselfwales\/selfie1525330290118-232x300.jpg","width":232,"height":300,"__typename":"MediaSize"},"full":{"sourceUrl":"https:\/\/dxlab.sl.nsw.gov.au\/images-newselfwales\/selfie1525330290118.jpg","width":813,"height":1050,"__typename":"MediaSize"},"__typename":"MediaSizes"},"__typename":"Media"},"__typename":"NewSelfWalesPortrait"},{"id":22949,"title":"Mr J. Laft (?)","primoId":"ADLIB110041862","slug":"adlib110041862","shortcode":"","imageUrl":"https:\/\/dxlab.sl.nsw.gov.au\/images-newselfwales\/selfie1525069550387.jpg","content":"interiors, portraits, Adult Males","imageType":"portrait","date":"2018-04-30 06:25:49","dateText":"1870-1875","timestamp":"","instagramUsername":"","featuredMedia":{"sourceUrl":"https:\/\/dxlab.sl.nsw.gov.au\/images-newselfwales\/selfie1525069550387.jpg","sizes":{"medium":{"sourceUrl":"https:\/\/dxlab.sl.nsw.gov.au\/images-newselfwales\/selfie1525069550387-223x300.jpg","width":223,"height":300,"__typename":"MediaSize"},"full":{"sourceUrl":"https:\/\/dxlab.sl.nsw.gov.au\/images-newselfwales\/selfie1525069550387.jpg","width":779,"height":1050,"__typename":"MediaSize"},"__typename":"MediaSizes"},"__typename":"Media"},"__typename":"NewSelfWalesPortrait"},{"id":56240,"title":"Musical comedy star Dorothy Brunton holding a small child","primoId":"ADLIB110001962","slug":"adlib110001962","shortcode":"","imageUrl":"https:\/\/dxlab.sl.nsw.gov.au\/images-newselfwales\/selfie1526376801493.jpg","content":"portraits, singers, St. Margaret's Hospital for Women (Darlinghurst, N.S.W.), Adult Females, babies","imageType":"portrait","date":"2018-05-15 09:33:21","dateText":"Jan 1925","timestamp":"","instagramUsername":"","featuredMedia":{"sourceUrl":"https:\/\/dxlab.sl.nsw.gov.au\/images-newselfwales\/selfie1526376801493.jpg","sizes":{"medium":{"sourceUrl":"https:\/\/dxlab.sl.nsw.gov.au\/images-newselfwales\/selfie1526376801493-e1534816908539-300x206.jpg","width":300,"height":206,"__typename":"MediaSize"},"full":{"sourceUrl":"https:\/\/dxlab.sl.nsw.gov.au\/images-newselfwales\/selfie1526376801493.jpg","width":1316,"height":903,"__typename":"MediaSize"},"__typename":"MediaSizes"},"__typename":"Media"},"__typename":"NewSelfWalesPortrait"},{"id":66316,"title":"Water ballet, January 1940 \/ photographed by S. Farnell and Ivan Ives","primoId":"ADLIB110372675","slug":"adlib110372675-fl815522","shortcode":"","imageUrl":"https:\/\/dxlab.sl.nsw.gov.au\/images-newselfwales\/selfie-1535621061659-.jpg","content":"","imageType":"portrait","date":"2018-09-03 15:46:13","dateText":"January 1940","timestamp":"","instagramUsername":"","featuredMedia":{"sourceUrl":"https:\/\/dxlab.sl.nsw.gov.au\/images-newselfwales\/selfie-1535621061659-.jpg","sizes":{"medium":{"sourceUrl":"https:\/\/dxlab.sl.nsw.gov.au\/images-newselfwales\/selfie-1535621061659--230x300.jpg","width":230,"height":300,"__typename":"MediaSize"},"full":{"sourceUrl":"https:\/\/dxlab.sl.nsw.gov.au\/images-newselfwales\/selfie-1535621061659-.jpg","width":805,"height":1050,"__typename":"MediaSize"},"__typename":"MediaSizes"},"__typename":"Media"},"__typename":"NewSelfWalesPortrait"},{"id":52594,"title":"Cottage and woman, Hill End","primoId":"ADLIB110040684","slug":"adlib110040684","shortcode":"","imageUrl":"https:\/\/dxlab.sl.nsw.gov.au\/images-newselfwales\/selfie1525940727371.jpg","content":"bark roofs, historic buildings, houses, portraits, Hill End (N.S.W.), Adult Females","imageType":"portrait","date":"2018-05-10 08:25:27","dateText":"1870-1875","timestamp":"","instagramUsername":"","featuredMedia":{"sourceUrl":"https:\/\/dxlab.sl.nsw.gov.au\/images-newselfwales\/selfie1525940727371.jpg","sizes":{"medium":{"sourceUrl":"https:\/\/dxlab.sl.nsw.gov.au\/images-newselfwales\/selfie1525940727371-300x226.jpg","width":300,"height":226,"__typename":"MediaSize"},"full":{"sourceUrl":"https:\/\/dxlab.sl.nsw.gov.au\/images-newselfwales\/selfie1525940727371.jpg","width":1400,"height":1053,"__typename":"MediaSize"},"__typename":"MediaSizes"},"__typename":"Media"},"__typename":"NewSelfWalesPortrait"},{"id":53664,"title":"Mssrs White [left] &amp; Hewitt in Royal Black Preceptory insignia","primoId":"ADLIB110042253","slug":"adlib110042253","shortcode":"","imageUrl":"https:\/\/dxlab.sl.nsw.gov.au\/images-newselfwales\/selfie1525947164427.jpg","content":"interiors, clubs, associations, societies etc., friendly societies, insignia, portraits, Adult Males","imageType":"portrait","date":"2018-05-10 10:12:44","dateText":"1870-1875","timestamp":"","instagramUsername":"","featuredMedia":{"sourceUrl":"https:\/\/dxlab.sl.nsw.gov.au\/images-newselfwales\/selfie1525947164427.jpg","sizes":{"medium":{"sourceUrl":"https:\/\/dxlab.sl.nsw.gov.au\/images-newselfwales\/selfie1525947164427-222x300.jpg","width":222,"height":300,"__typename":"MediaSize"},"full":{"sourceUrl":"https:\/\/dxlab.sl.nsw.gov.au\/images-newselfwales\/selfie1525947164427.jpg","width":777,"height":1050,"__typename":"MediaSize"},"__typename":"MediaSizes"},"__typename":"Media"},"__typename":"NewSelfWalesPortrait"},{"id":66392,"title":"Social [Summer activities - beach, tennis, picnics, pools, fashion]'s day and home, 25 December [1950?]","primoId":"ADLIB110372715","slug":"adlib110372715-fl665373","shortcode":"","imageUrl":"https:\/\/dxlab.sl.nsw.gov.au\/images-newselfwales\/selfie-1535621177444-.jpg","content":"","imageType":"portrait","date":"2018-09-03 15:45:41","dateText":"25 December [1950?]","timestamp":"","instagramUsername":"","featuredMedia":{"sourceUrl":"https:\/\/dxlab.sl.nsw.gov.au\/images-newselfwales\/selfie-1535621177444-.jpg","sizes":{"medium":{"sourceUrl":"https:\/\/dxlab.sl.nsw.gov.au\/images-newselfwales\/selfie-1535621177444--239x300.jpg","width":239,"height":300,"__typename":"MediaSize"},"full":{"sourceUrl":"https:\/\/dxlab.sl.nsw.gov.au\/images-newselfwales\/selfie-1535621177444-.jpg","width":837,"height":1050,"__typename":"MediaSize"},"__typename":"MediaSizes"},"__typename":"Media"},"__typename":"NewSelfWalesPortrait"},{"id":36112,"title":"Mr Cherry","primoId":"ADLIB110040929","slug":"adlib110040929","shortcode":"","imageUrl":"https:\/\/dxlab.sl.nsw.gov.au\/images-newselfwales\/selfie1525671909389.jpg","content":"interiors, portraits, Adult Males","imageType":"portrait","date":"2018-05-07 05:45:09","dateText":"1870-1875","timestamp":"","instagramUsername":"","featuredMedia":{"sourceUrl":"https:\/\/dxlab.sl.nsw.gov.au\/images-newselfwales\/selfie1525671909389.jpg","sizes":{"medium":{"sourceUrl":"https:\/\/dxlab.sl.nsw.gov.au\/images-newselfwales\/selfie1525671909389-224x300.jpg","width":224,"height":300,"__typename":"MediaSize"},"full":{"sourceUrl":"https:\/\/dxlab.sl.nsw.gov.au\/images-newselfwales\/selfie1525671909389.jpg","width":783,"height":1050,"__typename":"MediaSize"},"__typename":"MediaSizes"},"__typename":"Media"},"__typename":"NewSelfWalesPortrait"},{"id":51354,"title":"Middleweight boxing champion Pran Mikus","primoId":"ADLIB110045549","slug":"adlib110045549","shortcode":"","imageUrl":"https:\/\/dxlab.sl.nsw.gov.au\/images-newselfwales\/selfie1525934321778.jpg","content":"interiors, boxers, Photographs, portraits, Melbourne (Vic.), Adult Males","imageType":"portrait","date":"2018-05-10 06:38:41","dateText":"Sep 1955","timestamp":"","instagramUsername":"","featuredMedia":{"sourceUrl":"https:\/\/dxlab.sl.nsw.gov.au\/images-newselfwales\/selfie1525934321778.jpg","sizes":{"medium":{"sourceUrl":"https:\/\/dxlab.sl.nsw.gov.au\/images-newselfwales\/selfie1525934321778-300x210.jpg","width":300,"height":210,"__typename":"MediaSize"},"full":{"sourceUrl":"https:\/\/dxlab.sl.nsw.gov.au\/images-newselfwales\/selfie1525934321778.jpg","width":800,"height":560,"__typename":"MediaSize"},"__typename":"MediaSizes"},"__typename":"Media"},"__typename":"NewSelfWalesPortrait"},{"id":53558,"title":"Henrietta Watson, actor, 1899-1900 \/ Talma, 374 George St., Sydney. and at 119 Swanston St., Melbourne","primoId":"ADLIB110326998","slug":"adlib110326998","shortcode":"","imageUrl":"https:\/\/dxlab.sl.nsw.gov.au\/images-newselfwales\/selfie1525946465159.jpg","content":"actors, pirates, portraits, sailor suits, theatrical costumes, cross dressers, Adult Females","imageType":"portrait","date":"2018-05-10 10:01:05","dateText":"1899-1900","timestamp":"","instagramUsername":"","featuredMedia":{"sourceUrl":"https:\/\/dxlab.sl.nsw.gov.au\/images-newselfwales\/selfie1525946465159.jpg","sizes":{"medium":{"sourceUrl":"https:\/\/dxlab.sl.nsw.gov.au\/images-newselfwales\/selfie1525946465159-211x300.jpg","width":211,"height":300,"__typename":"MediaSize"},"full":{"sourceUrl":"https:\/\/dxlab.sl.nsw.gov.au\/images-newselfwales\/selfie1525946465159.jpg","width":738,"height":1050,"__typename":"MediaSize"},"__typename":"MediaSizes"},"__typename":"Media"},"__typename":"NewSelfWalesPortrait"},{"id":47919,"title":"Arrivals; George Gee (taken for J.C. Williamson)","primoId":"ADLIB110015590","slug":"adlib110015590","shortcode":"","imageUrl":"https:\/\/dxlab.sl.nsw.gov.au\/images-newselfwales\/selfie1525919782619.jpg","content":"performers, portraits, Sydney (N.S.W.), Adult Males","imageType":"portrait","date":"2018-05-10 02:36:22","dateText":"24\/9\/1937","timestamp":"","instagramUsername":"","featuredMedia":{"sourceUrl":"https:\/\/dxlab.sl.nsw.gov.au\/images-newselfwales\/selfie1525919782619.jpg","sizes":{"medium":{"sourceUrl":"https:\/\/dxlab.sl.nsw.gov.au\/images-newselfwales\/selfie1525919782619-300x226.jpg","width":300,"height":226,"__typename":"MediaSize"},"full":{"sourceUrl":"https:\/\/dxlab.sl.nsw.gov.au\/images-newselfwales\/selfie1525919782619.jpg","width":1400,"height":1055,"__typename":"MediaSize"},"__typename":"MediaSizes"},"__typename":"Media"},"__typename":"NewSelfWalesPortrait"},{"id":67458,"title":"Jess Prakash","primoId":"","slug":"","shortcode":"BmaWm1Zn8z1","imageUrl":"https:\/\/dxlab.sl.nsw.gov.au\/images-newselfwales\/selfie-1535700015274-.jpg","content":"Life is all about changing and growing... meet Jess 2.0, transformed myself just a little. Swipe right ;) #transformation #change #justalittlecut #byebyelonglocks #lob #newselfwales","imageType":"instagram_selfie","date":"2018-09-03 09:11:31","dateText":"","timestamp":1534147783,"instagramUsername":"jess.prakash","featuredMedia":{"sourceUrl":"https:\/\/dxlab.sl.nsw.gov.au\/images-newselfwales\/selfie-1535700015274-.jpg","sizes":{"medium":{"sourceUrl":"https:\/\/dxlab.sl.nsw.gov.au\/images-newselfwales\/selfie-1535700015274--300x300.jpg","width":300,"height":300,"__typename":"MediaSize"},"full":{"sourceUrl":"https:\/\/dxlab.sl.nsw.gov.au\/images-newselfwales\/selfie-1535700015274-.jpg","width":1080,"height":1080,"__typename":"MediaSize"},"__typename":"MediaSizes"},"__typename":"Media"},"__typename":"NewSelfWalesInstagramSelfie"},{"id":71643,"title":"Jill Myer","primoId":"","slug":"","shortcode":"BnzaSUxBs-V","imageUrl":"https:\/\/dxlab.sl.nsw.gov.au\/images-newselfwales\/selfie-1537136403726-.jpg","content":"#NewSelfWales","imageType":"instagram_selfie","date":"2018-09-17 10:49:25","dateText":"","timestamp":1537135895,"instagramUsername":"jill_myer","featuredMedia":{"sourceUrl":"https:\/\/dxlab.sl.nsw.gov.au\/images-newselfwales\/selfie-1537136403726-.jpg","sizes":{"medium":{"sourceUrl":"https:\/\/dxlab.sl.nsw.gov.au\/images-newselfwales\/selfie-1537136403726--300x300.jpg","width":300,"height":300,"__typename":"MediaSize"},"full":{"sourceUrl":"https:\/\/dxlab.sl.nsw.gov.au\/images-newselfwales\/selfie-1537136403726-.jpg","width":1049,"height":1049,"__typename":"MediaSize"},"__typename":"MediaSizes"},"__typename":"Media"},"__typename":"NewSelfWalesInstagramSelfie"},{"id":69219,"title":"Chew Suen Yee","primoId":"","slug":"","shortcode":"BnbGoWWAYY2","imageUrl":"https:\/\/dxlab.sl.nsw.gov.au\/images-newselfwales\/selfie-1536320404178-.jpg","content":"#newselfwales @statelibrarynsw #everydaywithxianyang","imageType":"instagram_selfie","date":"2018-09-10 10:01:22","dateText":"","timestamp":1536320283,"instagramUsername":"suenyee","featuredMedia":{"sourceUrl":"https:\/\/dxlab.sl.nsw.gov.au\/images-newselfwales\/selfie-1536320404178-.jpg","sizes":{"medium":{"sourceUrl":"https:\/\/dxlab.sl.nsw.gov.au\/images-newselfwales\/selfie-1536320404178--300x298.jpg","width":300,"height":298,"__typename":"MediaSize"},"full":{"sourceUrl":"https:\/\/dxlab.sl.nsw.gov.au\/images-newselfwales\/selfie-1536320404178-.jpg","width":1080,"height":1074,"__typename":"MediaSize"},"__typename":"MediaSizes"},"__typename":"Media"},"__typename":"NewSelfWalesInstagramSelfie"},{"id":68583,"title":"Tess &amp; David","primoId":"","slug":"","shortcode":"BnTBVAXlQ6I","imageUrl":"https:\/\/dxlab.sl.nsw.gov.au\/images-newselfwales\/selfie-1536049203310-.jpg","content":"#newselfwales","imageType":"instagram_selfie","date":"2018-09-07 09:39:21","dateText":"","timestamp":1536049068,"instagramUsername":"thecalopezzys","featuredMedia":{"sourceUrl":"https:\/\/dxlab.sl.nsw.gov.au\/images-newselfwales\/selfie-1536049203310-.jpg","sizes":{"medium":{"sourceUrl":"https:\/\/dxlab.sl.nsw.gov.au\/images-newselfwales\/selfie-1536049203310--300x300.jpg","width":300,"height":300,"__typename":"MediaSize"},"full":{"sourceUrl":"https:\/\/dxlab.sl.nsw.gov.au\/images-newselfwales\/selfie-1536049203310-.jpg","width":1080,"height":1078,"__typename":"MediaSize"},"__typename":"MediaSizes"},"__typename":"Media"},"__typename":"NewSelfWalesInstagramSelfie"},{"id":94031,"title":"bumzi","primoId":"","slug":"","shortcode":"","imageUrl":"https:\/\/dxlab.sl.nsw.gov.au\/images-newselfwales\/selfie-1544507827539.png","content":"bumzi","imageType":"gallery_selfie","date":"2018-12-11 16:57:07","dateText":"","timestamp":"","instagramUsername":"","featuredMedia":{"sourceUrl":"https:\/\/dxlab.sl.nsw.gov.au\/images-newselfwales\/selfie-1544507827539.png","sizes":{"medium":{"sourceUrl":"https:\/\/dxlab.sl.nsw.gov.au\/images-newselfwales\/selfie-1544507827539-300x300.png","width":300,"height":300,"__typename":"MediaSize"},"full":{"sourceUrl":"https:\/\/dxlab.sl.nsw.gov.au\/images-newselfwales\/selfie-1544507827539.png","width":1080,"height":1080,"__typename":"MediaSize"},"__typename":"MediaSizes"},"__typename":"Media"},"__typename":"NewSelfWalesGallerySelfie"},{"id":78750,"title":"elissa ferris","primoId":"","slug":"","shortcode":"","imageUrl":"https:\/\/dxlab.sl.nsw.gov.au\/images-newselfwales\/selfie-1539496028437.png","content":"elissa ferris","imageType":"gallery_selfie","date":"2018-10-14 15:47:08","dateText":"","timestamp":"","instagramUsername":"","featuredMedia":{"sourceUrl":"https:\/\/dxlab.sl.nsw.gov.au\/images-newselfwales\/selfie-1539496028437.png","sizes":{"medium":{"sourceUrl":"https:\/\/dxlab.sl.nsw.gov.au\/images-newselfwales\/selfie-1539496028437-300x300.png","width":300,"height":300,"__typename":"MediaSize"},"full":{"sourceUrl":"https:\/\/dxlab.sl.nsw.gov.au\/images-newselfwales\/selfie-1539496028437.png","width":1080,"height":1080,"__typename":"MediaSize"},"__typename":"MediaSizes"},"__typename":"Media"},"__typename":"NewSelfWalesGallerySelfie"},{"id":96162,"title":"Avani Gogi Saeka","primoId":"","slug":"","shortcode":"","imageUrl":"https:\/\/dxlab.sl.nsw.gov.au\/images-newselfwales\/selfie-1545270250206.png","content":"Avani Gogi Saeka","imageType":"gallery_selfie","date":"2018-12-20 12:44:10","dateText":"","timestamp":"","instagramUsername":"","featuredMedia":{"sourceUrl":"https:\/\/dxlab.sl.nsw.gov.au\/images-newselfwales\/selfie-1545270250206.png","sizes":{"medium":{"sourceUrl":"https:\/\/dxlab.sl.nsw.gov.au\/images-newselfwales\/selfie-1545270250206-300x300.png","width":300,"height":300,"__typename":"MediaSize"},"full":{"sourceUrl":"https:\/\/dxlab.sl.nsw.gov.au\/images-newselfwales\/selfie-1545270250206.png","width":1080,"height":1080,"__typename":"MediaSize"},"__typename":"MediaSizes"},"__typename":"Media"},"__typename":"NewSelfWalesGallerySelfie"},{"id":110690,"title":"dan harper","primoId":"","slug":"","shortcode":"","imageUrl":"https:\/\/dxlab.sl.nsw.gov.au\/images-newselfwales\/selfie-1549929561746.png","content":"dan harper","imageType":"gallery_selfie","date":"2019-02-12 10:59:21","dateText":"","timestamp":"","instagramUsername":"","featuredMedia":{"sourceUrl":"https:\/\/dxlab.sl.nsw.gov.au\/images-newselfwales\/selfie-1549929561746.png","sizes":{"medium":{"sourceUrl":"https:\/\/dxlab.sl.nsw.gov.au\/images-newselfwales\/selfie-1549929561746-300x300.png","width":300,"height":300,"__typename":"MediaSize"},"full":{"sourceUrl":"https:\/\/dxlab.sl.nsw.gov.au\/images-newselfwales\/selfie-1549929561746.png","width":1080,"height":1080,"__typename":"MediaSize"},"__typename":"MediaSizes"},"__typename":"Media"},"__typename":"NewSelfWalesGallerySelfie"}]}